energyplus_python_apps/__init__.py
energyplus_python_apps/configure.py
energyplus_python_apps-24.2a1.dist-info/LICENSE.txt
energyplus_python_apps-24.2a1.dist-info/METADATA
energyplus_python_apps-24.2a1.dist-info/WHEEL
energyplus_python_apps-24.2a1.dist-info/entry_points.txt
energyplus_python_apps-24.2a1.dist-info/top_level.txt
energyplus_python_apps-24.2a1.dist-info/RECORD
