Metadata-Version: 2.1
Name: energyplus-python-apps
Version: 24.2a1
Summary: Meta-package collecting all official EnergyPlus Python utilities
Home-page: https://github.com/Myoldmopar/EnergyPlusPythonApps
Author: Edwin Lee, for NREL, for United States Department of Energy
License: ModifiedBSD
Platform: UNKNOWN
Requires-Dist: energyplus-launch >=3.7.2
Requires-Dist: energyplus-ruleset-model >=0.5
Requires-Dist: energyplus-transition-tools >=2.0.8
Requires-Dist: energyplus-pet >=0.62
Requires-Dist: energyplus-idd-idf-utilities >=0.88
Requires-Dist: energyplus-regressions >=2.0.7
Requires-Dist: energyplus-api-helpers >=0.4
Requires-Dist: energyplus-diff-analysis >=0.2
Requires-Dist: energyplus-version >=1.0.0
